aind_codeocean_api/__init__.py
aind_codeocean_api/codeocean.py
aind_codeocean_api/credentials.py
aind_codeocean_api/py.typed
aind_codeocean_api/models/__init__.py
aind_codeocean_api/models/basic_request.py
aind_codeocean_api/models/computations_requests.py
aind_codeocean_api/models/data_assets_requests.py
aind_codeocean_api-0.5.1.dist-info/LICENSE
aind_codeocean_api-0.5.1.dist-info/METADATA
aind_codeocean_api-0.5.1.dist-info/WHEEL
aind_codeocean_api-0.5.1.dist-info/top_level.txt
aind_codeocean_api-0.5.1.dist-info/RECORD
