Metadata-Version: 2.1
Name: aind_codeocean_api
Version: 0.5.1
Summary: CodeOcean API manager in Python
Author: Allen Institute for Neural Dynamics
License: MIT
Classifier: Programming Language :: Python :: 3
Requires-Python: >=3.7
License-File: LICENSE
Requires-Dist: requests
Requires-Dist: pydantic >=2.0
Requires-Dist: pydantic-settings >=2.0
Requires-Dist: boto3
Provides-Extra: dev
Requires-Dist: black ; extra == 'dev'
Requires-Dist: coverage ; extra == 'dev'
Requires-Dist: flake8 ; extra == 'dev'
Requires-Dist: interrogate ; extra == 'dev'
Requires-Dist: isort ; extra == 'dev'
Requires-Dist: Sphinx ; extra == 'dev'
Requires-Dist: furo ; extra == 'dev'
Requires-Dist: python-dotenv ; extra == 'dev'
